{
	"version": "0.2",
	"language": "en,lorem",
	"ignorePaths": [
		".next/**",
		".vscode/**",
		".yarn/**",
		"node_modules/**",
		".eslintrc",
		"next.config.js",
		"package.json",
		"yarn.lock"
	],
	"allowCompoundWords": false,
	"words": [
		"atrule",
		"chakra",
		"Consolas",
		"Cyclomatic",
		"hireme",
		"Menlo",
		"monospace",
		"Noto",
		"Pluggable",
		"prefetch",
		"prettierrc",
		"Puccinelli",
		"Qube",
		"rehype",
		"slategray",
		"SMACSS",
		"sonarjs",
		"Tiso",
		"tripetto",
		"Vercel"
	]
}
